{
    "type": "Feature",
    "geometry": {
        "type": "Point",
        "coordinates": [
            -100.5571,
            25.3637
        ]
    },
    "properties": {
        "feet": 12178.47808,
        "meters": 3712.0,
        "latitude": 25.3637,
        "longitude": -100.5571,
        "name": "Cerro San Rafael",
        "countries": [
            "Mexico"
        ],
        "continent": "North America",
        "marker-size": "medium",
        "marker-symbol": "triangle"
    }
}