{
    "type": "Feature",
    "geometry": {
        "type": "Point",
        "coordinates": [
            -151.0074,
            63.0695
        ]
    },
    "properties": {
        "feet": 20310.0,
        "meters": 6190.48780190439,
        "latitude": 63.0695,
        "longitude": -151.0074,
        "name": "Denali",
        "countries": [
            "United States"
        ],
        "continent": "North America",
        "marker-size": "large",
        "marker-symbol": "triangle"
    }
}