{
    "type": "Feature",
    "geometry": {
        "type": "Point",
        "coordinates": [
            -110.3728151,
            40.7763818
        ]
    },
    "properties": {
        "feet": 13528.0,
        "meters": 4123.334268053303,
        "latitude": 40.7763818,
        "longitude": -110.3728151,
        "name": "Kings Peak",
        "countries": [
            "United States"
        ],
        "continent": "North America",
        "marker-size": "medium",
        "marker-symbol": "triangle"
    }
}