{
    "type": "Feature",
    "geometry": {
        "type": "Point",
        "coordinates": [
            -82.2651221,
            35.764839
        ]
    },
    "properties": {
        "feet": 6684.0,
        "meters": 2037.2831348069396,
        "latitude": 35.764839,
        "longitude": -82.2651221,
        "name": "Mount Mitchell",
        "countries": [
            "United States"
        ],
        "continent": "North America",
        "marker-size": "medium",
        "marker-symbol": "triangle"
    }
}