{
    "type": "Feature",
    "geometry": {
        "type": "Point",
        "coordinates": [
            -117.2923994,
            45.2448735
        ]
    },
    "properties": {
        "feet": 9843.0,
        "meters": 3000.1463039953182,
        "latitude": 45.2448735,
        "longitude": -117.2923994,
        "name": "Sacajawea Peak",
        "countries": [
            "United States"
        ],
        "continent": "North America",
        "marker-size": "medium",
        "marker-symbol": "triangle"
    }
}