{
    "type": "Feature",
    "geometry": {
        "type": "Point",
        "coordinates": [
            -123.09861,
            50.58361
        ]
    },
    "properties": {
        "feet": 7670.60392,
        "meters": 2338.0,
        "latitude": 50.58361,
        "longitude": -123.09861,
        "name": "Handcar Peak",
        "countries": [
            "British Indian Ocean Territory"
        ],
        "continent": "Asia",
        "marker-size": "medium",
        "marker-symbol": "triangle"
    }
}