{
    "type": "Feature",
    "geometry": {
        "type": "Point",
        "coordinates": [
            7.02444,
            45.91639
        ]
    },
    "properties": {
        "feet": 12696.8508,
        "meters": 3870.0,
        "latitude": 45.91639,
        "longitude": 7.02444,
        "name": "Aiguille de Triolet",
        "countries": [
            "Italy"
        ],
        "continent": "Europe",
        "marker-size": "medium",
        "marker-symbol": "triangle"
    }
}