{
    "type": "Feature",
    "geometry": {
        "type": "Point",
        "coordinates": [
            6.88,
            45.82778
        ]
    },
    "properties": {
        "feet": 13920.60412,
        "meters": 4243.0,
        "latitude": 45.82778,
        "longitude": 6.88,
        "name": "Grand Pilier d%27Angle",
        "countries": [
            "Philippines"
        ],
        "continent": "Asia",
        "marker-size": "large",
        "marker-symbol": "triangle"
    }
}