{
    "type": "Feature",
    "geometry": {
        "type": "Point",
        "coordinates": [
            24.59583,
            48.09167
        ]
    },
    "properties": {
        "feet": 6555.11832,
        "meters": 1998.0,
        "latitude": 48.09167,
        "longitude": 24.59583,
        "name": "Menchul",
        "countries": [
            "Ukraine"
        ],
        "continent": "Europe",
        "marker-size": "medium",
        "marker-symbol": "triangle"
    }
}