{
    "type": "Feature",
    "geometry": {
        "type": "Point",
        "coordinates": [
            -125.74694,
            49.66278
        ]
    },
    "properties": {
        "feet": 7201.4438,
        "meters": 2195.0,
        "latitude": 49.66278,
        "longitude": -125.74694,
        "name": "Golden Hinde",
        "countries": [
            "Canada"
        ],
        "continent": "North America",
        "marker-size": "medium",
        "marker-symbol": "triangle"
    }
}