{
    "type": "Feature",
    "geometry": {
        "type": "Point",
        "coordinates": [
            8.80833,
            46.91056
        ]
    },
    "properties": {
        "feet": 7808.3992,
        "meters": 2380.0,
        "latitude": 46.91056,
        "longitude": 8.80833,
        "name": "Alpler Horn",
        "countries": [
            "Switzerland"
        ],
        "continent": "Europe",
        "marker-size": "medium",
        "marker-symbol": "triangle"
    }
}