{
    "type": "Feature",
    "geometry": {
        "type": "Point",
        "coordinates": [
            8.68083,
            46.83083
        ]
    },
    "properties": {
        "feet": 7926.50944,
        "meters": 2416.0,
        "latitude": 46.83083,
        "longitude": 8.68083,
        "name": "B%C3%A4lmeten",
        "countries": [
            "Switzerland"
        ],
        "continent": "Europe",
        "marker-size": "medium",
        "marker-symbol": "triangle"
    }
}