{
    "type": "Feature",
    "geometry": {
        "type": "Point",
        "coordinates": [
            7.30889,
            46.01417
        ]
    },
    "properties": {
        "feet": 9019.02916,
        "meters": 2749.0,
        "latitude": 46.01417,
        "longitude": 7.30889,
        "name": "Becca de Corbassi%C3%A8re",
        "countries": [
            "Switzerland"
        ],
        "continent": "Europe",
        "marker-size": "medium",
        "marker-symbol": "triangle"
    }
}