{
    "type": "Feature",
    "geometry": {
        "type": "Point",
        "coordinates": [
            7.51833,
            46.16806
        ]
    },
    "properties": {
        "feet": 10331.36516,
        "meters": 3149.0,
        "latitude": 46.16806,
        "longitude": 7.51833,
        "name": "Becs de Bosson",
        "countries": [
            "Switzerland"
        ],
        "continent": "Europe",
        "marker-size": "medium",
        "marker-symbol": "triangle"
    }
}