{
    "type": "Feature",
    "geometry": {
        "type": "Point",
        "coordinates": [
            7.05944,
            47.13306
        ]
    },
    "properties": {
        "feet": 5269.02904,
        "meters": 1606.0,
        "latitude": 47.13306,
        "longitude": 7.05944,
        "name": "Chasseral",
        "countries": [
            "Switzerland"
        ],
        "continent": "Europe",
        "marker-size": "medium",
        "marker-symbol": "triangle"
    }
}