{
    "type": "Feature",
    "geometry": {
        "type": "Point",
        "coordinates": [
            7.867056,
            45.936833
        ]
    },
    "properties": {
        "feet": 15203.41256,
        "meters": 4634.0,
        "latitude": 45.936833,
        "longitude": 7.867056,
        "name": "Dufourspitze",
        "countries": [
            "Switzerland"
        ],
        "continent": "Europe",
        "marker-size": "large",
        "marker-symbol": "triangle"
    }
}