{
    "type": "Feature",
    "geometry": {
        "type": "Point",
        "coordinates": [
            7.72972,
            45.93833
        ]
    },
    "properties": {
        "feet": 12739.50172,
        "meters": 3883.0,
        "latitude": 45.93833,
        "longitude": 7.72972,
        "name": "Klein Matterhorn",
        "countries": [
            "Switzerland"
        ],
        "continent": "Europe",
        "marker-size": "medium",
        "marker-symbol": "triangle"
    }
}