{
    "type": "Feature",
    "geometry": {
        "type": "Point",
        "coordinates": [
            7.34444,
            45.91528
        ]
    },
    "properties": {
        "feet": 10980.97148,
        "meters": 3347.0,
        "latitude": 45.91528,
        "longitude": 7.34444,
        "name": "Mont Avril",
        "countries": [
            "Switzerland"
        ],
        "continent": "Europe",
        "marker-size": "medium",
        "marker-symbol": "triangle"
    }
}