{
    "type": "Feature",
    "geometry": {
        "type": "Point",
        "coordinates": [
            7.52861,
            46.40028
        ]
    },
    "properties": {
        "feet": 10643.04496,
        "meters": 3244.0,
        "latitude": 46.40028,
        "longitude": 7.52861,
        "name": "Wildstrubel",
        "countries": [
            "Switzerland"
        ],
        "continent": "Europe",
        "marker-size": "medium",
        "marker-symbol": "triangle"
    }
}