{
    "type": "Feature",
    "geometry": {
        "type": "Point",
        "coordinates": [
            7.69,
            46.06472
        ]
    },
    "properties": {
        "feet": 13848.42564,
        "meters": 4221.0,
        "latitude": 46.06472,
        "longitude": 7.69,
        "name": "Zinalrothorn",
        "countries": [
            "Switzerland"
        ],
        "continent": "Europe",
        "marker-size": "large",
        "marker-symbol": "triangle"
    }
}