{
    "type": "Feature",
    "geometry": {
        "type": "Point",
        "coordinates": [
            -76.83583,
            19.98944
        ]
    },
    "properties": {
        "feet": 6476.37816,
        "meters": 1974.0,
        "latitude": 19.98944,
        "longitude": -76.83583,
        "name": "Pico Turquino",
        "countries": [
            "Cuba"
        ],
        "continent": "North America",
        "marker-size": "medium",
        "marker-symbol": "triangle"
    }
}