{
    "type": "Feature",
    "geometry": {
        "type": "Point",
        "coordinates": [
            6.88722,
            45.87861
        ]
    },
    "properties": {
        "feet": 12604.98728,
        "meters": 3842.0,
        "latitude": 45.87861,
        "longitude": 6.88722,
        "name": "Aiguille du Midi",
        "countries": [
            "France"
        ],
        "continent": "Europe",
        "marker-size": "medium",
        "marker-symbol": "triangle"
    }
}