{
    "type": "Feature",
    "geometry": {
        "type": "Point",
        "coordinates": [
            6.35611,
            44.885
        ]
    },
    "properties": {
        "feet": 12972.44136,
        "meters": 3954.0,
        "latitude": 44.885,
        "longitude": 6.35611,
        "name": "Ailefroide",
        "countries": [
            "France"
        ],
        "continent": "Europe",
        "marker-size": "medium",
        "marker-symbol": "triangle"
    }
}